{
  "id": 21230501,
  "username": "Chllsang",
  "description": "데스락 헤네스 탈릿사 마카라 프라이드 오베론 글루토니 포너 라루스 페티아 베네보렌티아 세에레 템페렌티나 말티다스 인스트리아 라스 에피트 엔비 카스티타스 \n\n\n\n\n\n\n\n\n",
  "about": null,
  "team_id": null,
  "team_role": null,
  "date_created": "2022-12-24T11:51:04.000Z",
  "date_last_played": "2023-02-06T12:17:05.000Z",
  "profile_views": 156,
  "kill_count": 606,
  "play_count": 137,
  "highest_score": 5559507,
  "picture": null,
  "displayPicture": true,
  "active": true,
  "ban_message": null,
  "ban_at": null,
  "coins": 66,
  "tier": 3,
  "xp": 135300,
  "migrated": false,
  "verified": false,
  "beta": false,
  "badges": [],
  "social_networks": [],
  "user_stats": {
    "user_id": 21230501,
    "rank_kc": 38023,
    "rank_kc_dirty": true,
    "rank_kc_updated_at": "2023-08-27T08:15:34.000Z",
    "rank_pc": 58876,
    "rank_pc_dirty": true,
    "rank_pc_updated_at": "2023-08-27T08:15:37.000Z",
    "rank_hs": 6383,
    "rank_hs_dirty": true,
    "rank_hs_updated_at": "2023-08-27T08:15:38.000Z",
    "created_at": "2024-01-14T23:50:37.000Z",
    "updated_at": "2023-08-27T08:15:38.000Z",
    "pd": null
  },
  "creations": {
    "maps": {
      "items": [],
      "count": 0
    },
    "skins": []
  },
  "archived_at": "2025-04-27T17:37:25.988Z"
}