{
  "id": 20965163,
  "username": "minijuan",
  "description": "hi i kill you per-2 reasons 1: you a teamer man or a lamprey reason 2: you atacck me",
  "about": "hola xd",
  "team_id": null,
  "team_role": null,
  "date_created": "2022-08-26T01:26:29.000Z",
  "date_last_played": "2023-05-16T22:53:01.000Z",
  "profile_views": 167,
  "kill_count": 1322,
  "play_count": 358,
  "highest_score": 4179159,
  "picture": "20965163-48d5d89c0d9c1534f696dbe094de3589.png",
  "displayPicture": true,
  "active": true,
  "ban_message": null,
  "ban_at": null,
  "coins": 71,
  "tier": 4,
  "xp": 217800,
  "migrated": false,
  "verified": false,
  "beta": false,
  "badges": [],
  "social_networks": [],
  "user_stats": {
    "user_id": 20965163,
    "rank_kc": 20132,
    "rank_kc_dirty": true,
    "rank_kc_updated_at": "2023-05-16T22:36:34.000Z",
    "rank_pc": 28375,
    "rank_pc_dirty": true,
    "rank_pc_updated_at": "2023-05-16T22:36:38.000Z",
    "rank_hs": 10392,
    "rank_hs_dirty": true,
    "rank_hs_updated_at": "2023-05-16T22:36:40.000Z",
    "created_at": "2023-07-04T02:29:35.000Z",
    "updated_at": "2023-05-16T22:53:01.000Z",
    "pd": null
  },
  "creations": {
    "maps": {
      "items": [],
      "count": 0
    },
    "skins": []
  },
  "archived_at": "2025-04-26T14:10:25.734Z"
}