{
  "id": 20825218,
  "username": "asciifish",
  "description": "GG and have a nice day!",
  "about": null,
  "team_id": null,
  "team_role": null,
  "date_created": "2021-12-27T20:44:40.000Z",
  "date_last_played": "2025-05-01T17:05:48.000Z",
  "profile_views": 53,
  "kill_count": 700,
  "play_count": 188,
  "highest_score": 2272231,
  "picture": "20753407-9a1f8bffd666dc2d0dfb03d1b9e0ed67.png",
  "displayPicture": true,
  "active": true,
  "ban_message": null,
  "ban_at": null,
  "coins": 264,
  "tier": 3,
  "xp": 99750,
  "migrated": false,
  "verified": false,
  "beta": false,
  "badges": [],
  "social_networks": [],
  "user_stats": {
    "user_id": 20825218,
    "rank_kc": 34577,
    "rank_kc_dirty": true,
    "rank_kc_updated_at": "2023-09-05T01:18:03.000Z",
    "rank_pc": 49031,
    "rank_pc_dirty": true,
    "rank_pc_updated_at": "2023-09-05T01:18:04.000Z",
    "rank_hs": 32328,
    "rank_hs_dirty": false,
    "rank_hs_updated_at": "2023-09-05T01:18:05.000Z",
    "created_at": "2025-05-01T17:05:48.000Z",
    "updated_at": "2025-05-01T17:05:48.000Z",
    "pd": {
      "played": 1,
      "won": 0,
      "ratio": 0
    }
  },
  "creations": {
    "maps": {
      "items": [],
      "count": 0
    },
    "skins": []
  },
  "archived_at": "2025-05-12T02:27:25.422Z"
}