{
  "id": 20764507,
  "username": "DipStickZ__",
  "description": "Please have a nice day and take care <3",
  "about": "Follow me on twitch, twitter and youtube! DipStickZ__",
  "team_id": null,
  "team_role": null,
  "date_created": "2021-10-06T01:20:57.000Z",
  "date_last_played": "2023-04-25T17:56:15.000Z",
  "profile_views": 3,
  "kill_count": 712,
  "play_count": 1150,
  "highest_score": 1424771,
  "picture": "20764507-4210f4b0e1a040817879bc17908b5d61b.png",
  "displayPicture": false,
  "active": true,
  "ban_message": null,
  "ban_at": null,
  "coins": 106,
  "tier": 1,
  "xp": 1050,
  "migrated": true,
  "verified": false,
  "beta": false,
  "badges": [],
  "social_networks": [],
  "user_stats": {
    "user_id": 20764507,
    "rank_kc": 35929,
    "rank_kc_dirty": false,
    "rank_kc_updated_at": "2024-01-20T21:39:29.000Z",
    "rank_pc": 11573,
    "rank_pc_dirty": false,
    "rank_pc_updated_at": "2024-01-20T21:39:50.000Z",
    "rank_hs": 64857,
    "rank_hs_dirty": false,
    "rank_hs_updated_at": "2024-01-20T21:40:25.000Z",
    "created_at": "2024-01-20T21:40:48.000Z",
    "updated_at": "2024-01-20T21:40:25.000Z",
    "pd": null
  },
  "creations": {
    "maps": {
      "items": [],
      "count": 0
    },
    "skins": []
  },
  "archived_at": "2025-05-11T19:08:08.089Z"
}