{
  "id": 20723459,
  "username": "Water",
  "description": null,
  "about": null,
  "team_id": null,
  "team_role": null,
  "date_created": "2021-05-03T15:00:31.000Z",
  "date_last_played": "2021-05-03T15:24:59.000Z",
  "profile_views": 7,
  "kill_count": 0,
  "play_count": 4,
  "highest_score": 86270,
  "picture": null,
  "displayPicture": true,
  "active": true,
  "ban_message": null,
  "ban_at": null,
  "coins": 2,
  "tier": 1,
  "xp": 0,
  "migrated": false,
  "verified": false,
  "beta": false,
  "badges": [],
  "social_networks": [],
  "user_stats": {
    "user_id": 20723459,
    "rank_kc": 448365,
    "rank_kc_dirty": false,
    "rank_kc_updated_at": "2023-11-28T21:35:15.000Z",
    "rank_pc": 284378,
    "rank_pc_dirty": false,
    "rank_pc_updated_at": "2023-11-28T21:35:18.000Z",
    "rank_hs": 348334,
    "rank_hs_dirty": false,
    "rank_hs_updated_at": "2023-11-28T21:35:19.000Z",
    "created_at": "2023-11-28T21:35:18.000Z",
    "updated_at": "2023-11-28T21:35:19.000Z",
    "pd": null
  },
  "creations": {
    "maps": {
      "items": [],
      "count": 0
    },
    "skins": []
  },
  "archived_at": "2025-05-11T14:07:50.386Z"
}