{
  "id": 21268587,
  "username": "GeorgeFIoyd",
  "description": "bldm",
  "about": "i hired derek to kill me",
  "team_id": null,
  "team_role": null,
  "date_created": "2023-02-15T05:26:41.000Z",
  "date_last_played": "2023-02-15T09:47:23.000Z",
  "profile_views": 12,
  "kill_count": 14,
  "play_count": 6,
  "highest_score": 0,
  "picture": null,
  "displayPicture": true,
  "active": true,
  "ban_message": null,
  "ban_at": null,
  "coins": 46,
  "tier": 1,
  "xp": 5400,
  "migrated": false,
  "verified": false,
  "beta": false,
  "badges": [],
  "social_networks": [
    {
      "id": 15097,
      "user_id": 21268587,
      "platform_id": "dc",
      "platform_user_id": "obama barak #6969",
      "platform_user_url": null,
      "verified": false,
      "created_at": "2023-02-15T05:28:31.000Z",
      "updated_at": "2023-02-15T05:28:31.000Z"
    },
    {
      "id": 15102,
      "user_id": 21268587,
      "platform_id": "dc",
      "platform_user_id": "why did micheal turn white?",
      "platform_user_url": null,
      "verified": false,
      "created_at": "2023-02-15T05:32:39.000Z",
      "updated_at": "2023-02-15T05:32:53.000Z"
    },
    {
      "id": 15098,
      "user_id": 21268587,
      "platform_id": "rd",
      "platform_user_id": "derek chauvin ",
      "platform_user_url": null,
      "verified": false,
      "created_at": "2023-02-15T05:29:07.000Z",
      "updated_at": "2023-02-15T05:29:07.000Z"
    },
    {
      "id": 15100,
      "user_id": 21268587,
      "platform_id": "yt",
      "platform_user_id": "is cool",
      "platform_user_url": "https://youtube.com/@",
      "verified": false,
      "created_at": "2023-02-15T05:31:05.000Z",
      "updated_at": "2023-02-15T05:31:05.000Z"
    }
  ],
  "user_stats": {
    "user_id": 21268587,
    "rank_kc_dirty": true,
    "rank_pc_dirty": true,
    "rank_hs_dirty": true,
    "created_at": "2025-04-27T22:00:14.944Z",
    "updated_at": "2025-04-27T22:00:15.000Z",
    "rank_kc": null,
    "rank_kc_updated_at": null,
    "rank_pc": null,
    "rank_pc_updated_at": null,
    "rank_hs": null,
    "rank_hs_updated_at": null,
    "pd": null
  },
  "creations": {
    "maps": {
      "items": [],
      "count": 0
    },
    "skins": []
  },
  "archived_at": "2025-04-27T22:00:15.037Z"
}