{
  "id": 20976203,
  "username": "평화자",
  "description": "죽여서 미안..\nI’m sorry..",
  "about": "평화를 사랑하는(아마도)(패드 유저입니다)평화자입니다.\ncall me ‘peacefulman’\n친한 유저:로그,조조조개,한치초밥\n게임 잘 못함.. 그래서 잘 안함\n적폐나 인기 많은캐는 잘 못씀\n주요 캐릭터:황상,곰치(둘다 개못함)",
  "team_id": null,
  "team_role": null,
  "date_created": "2022-10-05T05:44:49.000Z",
  "date_last_played": "2023-08-29T09:02:54.000Z",
  "profile_views": 1214,
  "kill_count": 1349,
  "play_count": 639,
  "highest_score": 4033383,
  "picture": "20976203-57cb5710a104a102a5cc772ef0207c39909.png",
  "displayPicture": true,
  "active": true,
  "ban_message": null,
  "ban_at": null,
  "coins": 1064,
  "tier": 5,
  "xp": 325800,
  "migrated": false,
  "verified": false,
  "beta": false,
  "badges": [],
  "social_networks": [],
  "user_stats": {
    "user_id": 20976203,
    "rank_kc": 21656,
    "rank_kc_dirty": true,
    "rank_kc_updated_at": "2023-11-19T12:23:03.000Z",
    "rank_pc": 20094,
    "rank_pc_dirty": true,
    "rank_pc_updated_at": "2023-11-19T12:23:09.000Z",
    "rank_hs": 12434,
    "rank_hs_dirty": true,
    "rank_hs_updated_at": "2023-11-19T12:23:12.000Z",
    "created_at": "2024-01-17T14:22:39.000Z",
    "updated_at": "2023-11-19T12:23:12.000Z",
    "pd": null
  },
  "creations": {
    "maps": {
      "items": [],
      "count": 0
    },
    "skins": []
  },
  "archived_at": "2025-04-26T15:23:14.290Z"
}