{
  "id": 21281691,
  "username": "Polentacz",
  "description": "HEHEHHEHEHA goofy ahh sorry btw :(    \n\nalso if you teamed FU** you! \n\nif you 1v1 me for points get out log out now! i hate that >:( \nNO hailbuts! jazzi is not cool also arc. just a note for glitchy my mains are goblin cs and elephant also moby poka",
  "about": "im the history nerd im goofy ah btw hi dwoo uwu oh yeah whatch sadnessified and swampseter yt! before i get you in your sleep :) i want MORE COINS see yall! i have been playing for 2 yrs! btw FU- frick teamers and toxic people like prorca. UTTM?",
  "team_id": null,
  "team_role": null,
  "date_created": "2023-04-12T00:15:55.000Z",
  "date_last_played": "2025-04-27T20:17:58.000Z",
  "profile_views": 1787,
  "kill_count": 5217,
  "play_count": 2315,
  "highest_score": 3727852,
  "picture": "21281691-0e8c74a3b5175c5b6643446b6a3d2e710-85f2d78f-dcae-45ed-a322-6935183f2fff.png",
  "displayPicture": true,
  "active": true,
  "ban_message": null,
  "ban_at": null,
  "coins": 2432,
  "tier": 10,
  "xp": 1203300,
  "migrated": false,
  "verified": false,
  "beta": false,
  "badges": [],
  "social_networks": [
    {
      "id": 93660,
      "user_id": 21281691,
      "platform_id": "yt",
      "platform_user_id": "https://www.youtube.com/channel/UCllXt3VMsMIuIZ34IZ0OJLg",
      "platform_user_url": "https://www.youtube.com/channel/UCllXt3VMsMIuIZ34IZ0OJLg",
      "verified": false,
      "created_at": "2024-04-07T17:34:34.000Z",
      "updated_at": "2024-04-07T17:34:34.000Z"
    }
  ],
  "user_stats": {
    "user_id": 21281691,
    "rank_kc": 14581,
    "rank_kc_dirty": true,
    "rank_kc_updated_at": "2023-11-27T21:45:39.000Z",
    "rank_pc": 14139,
    "rank_pc_dirty": true,
    "rank_pc_updated_at": "2023-11-27T21:45:41.000Z",
    "rank_hs": 44016,
    "rank_hs_dirty": true,
    "rank_hs_updated_at": "2023-11-27T21:45:42.000Z",
    "created_at": "2025-04-27T20:17:58.000Z",
    "updated_at": "2025-04-27T20:17:58.000Z",
    "pd": {
      "played": 6,
      "won": 6,
      "ratio": 100
    }
  },
  "creations": {
    "maps": {
      "items": [
        {
          "id": 43933,
          "user_id": 21281691,
          "cloneof_id": null,
          "string_id": "my_map_00000000890",
          "title": "the deep world",
          "description": "Poland?",
          "public": true,
          "locked": false,
          "clonable": false,
          "permissions": 1,
          "likes": 2,
          "objects": 38,
          "created_at": "2024-04-04T12:41:13.000Z",
          "updated_at": "2024-04-04T12:41:14.000Z",
          "deleted_at": null,
          "user": {
            "id": 21281691,
            "username": "Polentacz",
            "description": "HEHEHHEHEHA goofy ahh sorry btw :(    \n\nalso if you teamed FU** you! \n\nif you 1v1 me for points get out log out now! i hate that >:( \nNO hailbuts! jazzi is not cool also arc. just a note for glitchy my mains are goblin cs and elephant also moby poka",
            "about": "im the history nerd im goofy ah btw hi dwoo uwu oh yeah whatch sadnessified and swampseter yt! before i get you in your sleep :) i want MORE COINS see yall! i have been playing for 2 yrs! btw FU- frick teamers and toxic people like prorca. UTTM?",
            "team_id": null,
            "team_role": null,
            "date_created": "2023-04-12T00:15:55.000Z",
            "date_last_played": "2025-04-27T20:17:58.000Z",
            "kill_count": 5217,
            "play_count": 2315,
            "highest_score": 3727852,
            "picture": "21281691-0e8c74a3b5175c5b6643446b6a3d2e710-85f2d78f-dcae-45ed-a322-6935183f2fff.png",
            "displayPicture": true,
            "active": true,
            "ban_message": null,
            "ban_at": null,
            "coins": 2432,
            "tier": 10,
            "xp": 1203300,
            "migrated": false,
            "verified": false,
            "beta": false
          },
          "tags": []
        },
        {
          "id": 43931,
          "user_id": 21281691,
          "cloneof_id": null,
          "string_id": "my_map_v09999u979",
          "title": "polen?",
          "description": "it cool",
          "public": true,
          "locked": false,
          "clonable": false,
          "permissions": 1,
          "likes": 1,
          "objects": 63,
          "created_at": "2024-04-04T02:54:11.000Z",
          "updated_at": "2024-04-04T02:54:11.000Z",
          "deleted_at": null,
          "user": {
            "id": 21281691,
            "username": "Polentacz",
            "description": "HEHEHHEHEHA goofy ahh sorry btw :(    \n\nalso if you teamed FU** you! \n\nif you 1v1 me for points get out log out now! i hate that >:( \nNO hailbuts! jazzi is not cool also arc. just a note for glitchy my mains are goblin cs and elephant also moby poka",
            "about": "im the history nerd im goofy ah btw hi dwoo uwu oh yeah whatch sadnessified and swampseter yt! before i get you in your sleep :) i want MORE COINS see yall! i have been playing for 2 yrs! btw FU- frick teamers and toxic people like prorca. UTTM?",
            "team_id": null,
            "team_role": null,
            "date_created": "2023-04-12T00:15:55.000Z",
            "date_last_played": "2025-04-27T20:17:58.000Z",
            "kill_count": 5217,
            "play_count": 2315,
            "highest_score": 3727852,
            "picture": "21281691-0e8c74a3b5175c5b6643446b6a3d2e710-85f2d78f-dcae-45ed-a322-6935183f2fff.png",
            "displayPicture": true,
            "active": true,
            "ban_message": null,
            "ban_at": null,
            "coins": 2432,
            "tier": 10,
            "xp": 1203300,
            "migrated": false,
            "verified": false,
            "beta": false
          },
          "tags": []
        }
      ],
      "count": 2
    },
    "skins": []
  },
  "archived_at": "2025-04-27T23:21:32.748Z"
}