{
  "id": 20720137,
  "username": "DISCONNECTED",
  "description": "Loading...",
  "about": "--<><><>::::::::::::::::<><><>--",
  "team_id": null,
  "team_role": null,
  "date_created": "2021-04-24T18:03:01.000Z",
  "date_last_played": "2025-03-30T20:16:10.000Z",
  "profile_views": 68,
  "kill_count": 2312,
  "play_count": 826,
  "highest_score": 10100745,
  "picture": "20720137-4fd10787ee99c102f38e1fb19bc9784d5e.png",
  "displayPicture": true,
  "active": true,
  "ban_message": null,
  "ban_at": null,
  "coins": 189,
  "tier": 5,
  "xp": 257250,
  "migrated": false,
  "verified": false,
  "beta": false,
  "badges": [],
  "social_networks": [],
  "user_stats": {
    "user_id": 20720137,
    "rank_kc": 14483,
    "rank_kc_dirty": true,
    "rank_kc_updated_at": "2024-01-06T03:46:33.000Z",
    "rank_pc": 17096,
    "rank_pc_dirty": true,
    "rank_pc_updated_at": "2024-01-06T03:46:34.000Z",
    "rank_hs": 2652,
    "rank_hs_dirty": true,
    "rank_hs_updated_at": "2024-01-06T03:46:35.000Z",
    "created_at": "2025-03-30T20:16:09.000Z",
    "updated_at": "2025-03-30T20:16:10.000Z",
    "pd": null
  },
  "creations": {
    "maps": {
      "items": [],
      "count": 0
    },
    "skins": []
  },
  "archived_at": "2025-05-11T13:48:50.215Z"
}