{
  "id": 20778109,
  "username": "ShadxwGxdner™",
  "description": "See you in the Shadxws! ",
  "about": null,
  "team_id": null,
  "team_role": null,
  "date_created": "2021-11-11T23:03:18.000Z",
  "date_last_played": "2022-08-04T19:44:11.000Z",
  "profile_views": 5,
  "kill_count": 11,
  "play_count": 61,
  "highest_score": 324908,
  "picture": "20778109-79b176410960963b1bc149e571575deb7.png",
  "displayPicture": false,
  "active": true,
  "ban_message": null,
  "ban_at": null,
  "coins": 42,
  "tier": 1,
  "xp": 2400,
  "migrated": false,
  "verified": false,
  "beta": false,
  "badges": [],
  "social_networks": [],
  "user_stats": {
    "user_id": 20778109,
    "rank_kc": 369975,
    "rank_kc_dirty": true,
    "rank_kc_updated_at": "2022-08-03T02:18:56.000Z",
    "rank_pc": 223921,
    "rank_pc_dirty": true,
    "rank_pc_updated_at": "2022-08-03T02:18:56.000Z",
    "rank_hs": 474437,
    "rank_hs_dirty": true,
    "rank_hs_updated_at": "2022-08-03T02:18:57.000Z",
    "created_at": "2022-08-04T19:44:10.000Z",
    "updated_at": "2022-08-04T19:44:11.000Z",
    "pd": null
  },
  "creations": {
    "maps": {
      "items": [],
      "count": 0
    },
    "skins": []
  },
  "archived_at": "2025-05-11T20:54:19.440Z"
}