{
  "id": 20958347,
  "username": "vavatoo",
  "description": "hehe",
  "about": "\n\n",
  "team_id": null,
  "team_role": null,
  "date_created": "2022-07-29T08:37:11.000Z",
  "date_last_played": "2023-10-22T15:38:44.000Z",
  "profile_views": 243,
  "kill_count": 2287,
  "play_count": 516,
  "highest_score": 3867394,
  "picture": "20958347-168a3c4683a64a2642c512134acf68a2.png",
  "displayPicture": true,
  "active": true,
  "ban_message": null,
  "ban_at": null,
  "coins": 1019,
  "tier": 5,
  "xp": 313050,
  "migrated": false,
  "verified": false,
  "beta": false,
  "badges": [],
  "social_networks": [],
  "user_stats": {
    "user_id": 20958347,
    "rank_kc": 13794,
    "rank_kc_dirty": true,
    "rank_kc_updated_at": "2023-07-14T14:14:51.000Z",
    "rank_pc": 22735,
    "rank_pc_dirty": true,
    "rank_pc_updated_at": "2023-07-14T14:14:52.000Z",
    "rank_hs": 12578,
    "rank_hs_dirty": true,
    "rank_hs_updated_at": "2023-07-14T14:14:52.000Z",
    "created_at": "2023-10-22T15:38:44.000Z",
    "updated_at": "2023-10-22T15:38:44.000Z",
    "pd": null
  },
  "creations": {
    "maps": {
      "items": [],
      "count": 0
    },
    "skins": []
  },
  "archived_at": "2025-04-26T13:29:41.859Z"
}