{
  "id": 21293371,
  "username": "Susalob",
  "description": "SUB TO SUSALOB!",
  "about": "i am a sigma\n",
  "team_id": null,
  "team_role": null,
  "date_created": "2023-05-21T04:18:20.000Z",
  "date_last_played": "2024-07-29T21:51:06.000Z",
  "profile_views": 81,
  "kill_count": 37,
  "play_count": 218,
  "highest_score": 1068931,
  "picture": "21293371-b3676dbe2b59620e74409ccc64ee192a.png",
  "displayPicture": true,
  "active": true,
  "ban_message": null,
  "ban_at": null,
  "coins": 18,
  "tier": 1,
  "xp": 11700,
  "migrated": false,
  "verified": false,
  "beta": false,
  "badges": [],
  "social_networks": [
    {
      "id": 96911,
      "user_id": 21293371,
      "platform_id": "tw",
      "platform_user_id": "Susalob",
      "platform_user_url": null,
      "verified": false,
      "created_at": "2024-07-28T20:55:42.000Z",
      "updated_at": "2024-07-28T20:55:42.000Z"
    },
    {
      "id": 96910,
      "user_id": 21293371,
      "platform_id": "yt",
      "platform_user_id": "Susalob",
      "platform_user_url": "https://www.youtube.com/@Sub_2_Susalob",
      "verified": false,
      "created_at": "2024-07-28T20:55:22.000Z",
      "updated_at": "2024-07-28T20:55:22.000Z"
    }
  ],
  "user_stats": {
    "user_id": 21293371,
    "rank_kc": 202482,
    "rank_kc_dirty": true,
    "rank_kc_updated_at": "2023-06-23T05:33:46.000Z",
    "rank_pc": 45436,
    "rank_pc_dirty": true,
    "rank_pc_updated_at": "2023-06-23T05:33:47.000Z",
    "rank_hs": 116858,
    "rank_hs_dirty": true,
    "rank_hs_updated_at": "2023-06-23T05:33:48.000Z",
    "created_at": "2024-07-29T21:51:06.000Z",
    "updated_at": "2024-07-29T21:51:06.000Z",
    "pd": null
  },
  "creations": {
    "maps": {
      "items": [],
      "count": 0
    },
    "skins": []
  },
  "archived_at": "2025-04-28T00:39:09.916Z"
}