{
  "id": 545631,
  "username": "KnightLautrec",
  "description": "Oh, hello. I'm considering a change of location... I have a rather, pressing matter to attend to up above. That Keeper has served me well, but... Enough with her... Keh heh heh heh...\n",
  "about": null,
  "team_id": null,
  "team_role": null,
  "date_created": "2018-12-09T02:54:00.000Z",
  "date_last_played": "2023-03-09T00:02:02.000Z",
  "profile_views": 5,
  "kill_count": 782,
  "play_count": 247,
  "highest_score": 2683766,
  "picture": "545631-927cbfc7ee55588c90be96064b10e1dc.png",
  "displayPicture": false,
  "active": true,
  "ban_message": null,
  "ban_at": null,
  "coins": 130,
  "tier": 1,
  "xp": 300,
  "migrated": true,
  "verified": false,
  "beta": false,
  "badges": [],
  "social_networks": [],
  "user_stats": {
    "user_id": 545631,
    "rank_kc": null,
    "rank_kc_dirty": true,
    "rank_kc_updated_at": null,
    "rank_pc": null,
    "rank_pc_dirty": true,
    "rank_pc_updated_at": null,
    "rank_hs": null,
    "rank_hs_dirty": true,
    "rank_hs_updated_at": null,
    "created_at": "2025-04-24T05:19:50.000Z",
    "updated_at": "2025-04-24T05:19:50.000Z",
    "pd": null
  },
  "creations": {
    "maps": {
      "items": [],
      "count": 0
    },
    "skins": []
  },
  "archived_at": "2025-06-15T16:42:50.199Z"
}