{
  "id": 20977815,
  "username": "PetPaket",
  "description": "very sorry if i kill you, but remember, Its only game\nbye\n",
  "about": "very sorry if i kill you, but remember, Its only game\nbye\n",
  "team_id": null,
  "team_role": null,
  "date_created": "2022-10-11T19:24:29.000Z",
  "date_last_played": "2023-08-12T16:27:53.000Z",
  "profile_views": 109,
  "kill_count": 495,
  "play_count": 203,
  "highest_score": 1335441,
  "picture": "20977815-4b62102af2b28f78d44d973ffa77c7b3e.png",
  "displayPicture": true,
  "active": true,
  "ban_message": null,
  "ban_at": null,
  "coins": 35,
  "tier": 3,
  "xp": 87750,
  "migrated": false,
  "verified": false,
  "beta": false,
  "badges": [],
  "social_networks": [
    {
      "id": 8099,
      "user_id": 20977815,
      "platform_id": "dc",
      "platform_user_id": "PetPaket#6307",
      "platform_user_url": null,
      "verified": false,
      "created_at": "2022-10-15T16:14:58.000Z",
      "updated_at": "2022-10-15T16:15:16.000Z"
    }
  ],
  "user_stats": {
    "user_id": 20977815,
    "rank_kc": 44712,
    "rank_kc_dirty": false,
    "rank_kc_updated_at": "2023-11-10T21:33:51.000Z",
    "rank_pc": 47945,
    "rank_pc_dirty": false,
    "rank_pc_updated_at": "2023-11-10T21:33:54.000Z",
    "rank_hs": 67938,
    "rank_hs_dirty": true,
    "rank_hs_updated_at": "2023-11-10T21:33:56.000Z",
    "created_at": "2023-11-12T01:52:14.000Z",
    "updated_at": "2023-11-10T21:33:56.000Z",
    "pd": null
  },
  "creations": {
    "maps": {
      "items": [],
      "count": 0
    },
    "skins": []
  },
  "archived_at": "2025-04-26T15:33:00.426Z"
}