{
  "id": 21379058,
  "username": "🇷🇺RUSSO🇷🇺",
  "description": "OTARO",
  "about": "Não sou RUSSO e so um apelido dado por 3 anos atras por conta de eu ser praticamente um monstro no jogo dado por alguém que eu nem lembro \n",
  "team_id": null,
  "team_role": null,
  "date_created": "2024-08-24T22:45:00.000Z",
  "date_last_played": "2025-05-12T03:28:11.000Z",
  "profile_views": 82,
  "kill_count": 2230,
  "play_count": 2287,
  "highest_score": 2660608,
  "picture": "21379058-52b8af17ab28a8a1b1fb62653cb591036-31d92dc7-351e-4264-a67d-2c38154a96b9.png",
  "displayPicture": true,
  "active": true,
  "ban_message": null,
  "ban_at": null,
  "coins": 614,
  "tier": 8,
  "xp": 801150,
  "migrated": false,
  "verified": false,
  "beta": false,
  "badges": [],
  "social_networks": [],
  "user_stats": {
    "user_id": 21379058,
    "rank_kc": null,
    "rank_kc_dirty": true,
    "rank_kc_updated_at": null,
    "rank_pc": null,
    "rank_pc_dirty": true,
    "rank_pc_updated_at": null,
    "rank_hs": null,
    "rank_hs_dirty": true,
    "rank_hs_updated_at": null,
    "created_at": "2025-05-12T03:28:11.000Z",
    "updated_at": "2025-05-12T03:28:11.000Z",
    "pd": null
  },
  "creations": {
    "maps": {
      "items": [],
      "count": 0
    },
    "skins": []
  },
  "archived_at": "2025-05-14T19:09:12.911Z"
}