{
  "id": 21323004,
  "username": "jiseo",
  "description": "",
  "about": null,
  "team_id": null,
  "team_role": null,
  "date_created": "2023-10-06T02:29:04.000Z",
  "date_last_played": "2023-11-23T03:55:14.000Z",
  "profile_views": 9,
  "kill_count": 91,
  "play_count": 198,
  "highest_score": 773200,
  "picture": null,
  "displayPicture": true,
  "active": true,
  "ban_message": null,
  "ban_at": null,
  "coins": 57,
  "tier": 1,
  "xp": 17700,
  "migrated": false,
  "verified": false,
  "beta": false,
  "badges": [],
  "social_networks": [],
  "user_stats": {
    "user_id": 21323004,
    "rank_kc": 152767,
    "rank_kc_dirty": true,
    "rank_kc_updated_at": "2023-10-23T05:25:15.000Z",
    "rank_pc": 61701,
    "rank_pc_dirty": true,
    "rank_pc_updated_at": "2023-10-23T05:25:16.000Z",
    "rank_hs": 112758,
    "rank_hs_dirty": false,
    "rank_hs_updated_at": "2023-10-23T05:25:16.000Z",
    "created_at": "2023-11-23T03:55:14.000Z",
    "updated_at": "2023-11-23T03:55:14.000Z",
    "pd": null
  },
  "creations": {
    "maps": {
      "items": [],
      "count": 0
    },
    "skins": []
  },
  "archived_at": "2025-04-28T03:55:56.139Z"
}