{
  "id": 20780197,
  "username": "Brutes_Crux",
  "description": "Demonic spirit of the swamp. Horns grown, twisting, bracing. A skull to shatter any barrier.\n",
  "about": null,
  "team_id": null,
  "team_role": null,
  "date_created": "2021-11-19T07:53:16.000Z",
  "date_last_played": "2025-03-15T00:17:45.000Z",
  "profile_views": 105,
  "kill_count": 269,
  "play_count": 739,
  "highest_score": 1954389,
  "picture": "20780197-1042dd9e3e6c4428f5c8e2ceab69142f9-03730834-2a01-4905-9591-e253b52a9b29.png",
  "displayPicture": true,
  "active": true,
  "ban_message": null,
  "ban_at": null,
  "coins": 162,
  "tier": 3,
  "xp": 76800,
  "migrated": false,
  "verified": false,
  "beta": false,
  "badges": [],
  "social_networks": [],
  "user_stats": {
    "user_id": 20780197,
    "rank_kc": 72713,
    "rank_kc_dirty": true,
    "rank_kc_updated_at": "2023-12-14T23:54:22.000Z",
    "rank_pc": 20608,
    "rank_pc_dirty": true,
    "rank_pc_updated_at": "2023-12-14T23:54:30.000Z",
    "rank_hs": 42543,
    "rank_hs_dirty": false,
    "rank_hs_updated_at": "2023-12-14T23:54:34.000Z",
    "created_at": "2025-03-15T00:17:45.000Z",
    "updated_at": "2025-03-15T00:17:45.000Z",
    "pd": null
  },
  "creations": {
    "maps": {
      "items": [],
      "count": 0
    },
    "skins": []
  },
  "archived_at": "2025-05-11T21:06:46.543Z"
}