{
  "id": 20767761,
  "username": "Manslaughter",
  "description": "Whale ~ 4.5mil, 3.4mil\nPancake ~ 2mil\nOrca ~ 5.4mil \nShark ~ 3.4mil\nIm going to touch u ",
  "about": null,
  "team_id": null,
  "team_role": null,
  "date_created": "2021-10-17T00:07:03.000Z",
  "date_last_played": "2025-03-05T08:39:45.000Z",
  "profile_views": 60,
  "kill_count": 2224,
  "play_count": 1417,
  "highest_score": 4649753,
  "picture": null,
  "displayPicture": false,
  "active": true,
  "ban_message": null,
  "ban_at": null,
  "coins": 583,
  "tier": 6,
  "xp": 519150,
  "migrated": true,
  "verified": false,
  "beta": false,
  "badges": [],
  "social_networks": [],
  "user_stats": {
    "user_id": 20767761,
    "rank_kc": 24114,
    "rank_kc_dirty": true,
    "rank_kc_updated_at": "2023-10-28T03:39:44.000Z",
    "rank_pc": 18107,
    "rank_pc_dirty": true,
    "rank_pc_updated_at": "2023-10-28T03:39:45.000Z",
    "rank_hs": 9305,
    "rank_hs_dirty": true,
    "rank_hs_updated_at": "2023-10-28T03:39:48.000Z",
    "created_at": "2025-03-05T08:39:44.000Z",
    "updated_at": "2025-03-05T08:39:45.000Z",
    "pd": null
  },
  "creations": {
    "maps": {
      "items": [],
      "count": 0
    },
    "skins": []
  },
  "archived_at": "2025-05-11T19:37:46.164Z"
}